[   
    {
        "id":1,
        "fecha":"2021-10-15blue",
        "venta":222.210,
        "compra":105.480
    },
    {
        "id":2,
        "fecha":"2021-10-14",
        "venta":222.090,
        "compra":105.420
    },
    {
        "id":3,
        "fecha":"2021-10-13",
        "venta":222.070,
        "compra":105.390
    },
    {
        "id":4,
        "fecha":"2021-10-12",
        "venta":98.010,
        "compra":105.360
    },
    {
        "id":5,
        "fecha":"2021-10-11",
        "venta":97.920,
        "compra":105.270
    },
    {
        "id":6,
        "fecha":"2021-10-10",
        "venta":97.920,
        "compra":105.270
    },
    {
        "id":7,
        "fecha":"2021-10-09",
        "venta":97.920,
        "compra":105.270
    },
    {
        "id":8,
        "fecha":"2021-10-08",
        "venta":97.920,
        "compra":105.270
    },
    {
        "id":9,
        "fecha":"2021-10-07",
        "venta":97.920,
        "compra":105.270
    }
]